MANIFEST.in
README.md
setup.py
streamlit_pannellum/__init__.py
streamlit_pannellum/pypi_readme.md
streamlit_pannellum.egg-info/PKG-INFO
streamlit_pannellum.egg-info/SOURCES.txt
streamlit_pannellum.egg-info/dependency_links.txt
streamlit_pannellum.egg-info/requires.txt
streamlit_pannellum.egg-info/top_level.txt
streamlit_pannellum/frontend/dist/index.html
streamlit_pannellum/frontend/dist/vite.svg
streamlit_pannellum/frontend/dist/assets/index-0de0fe39.css
streamlit_pannellum/frontend/dist/assets/index-6409c266.js