Metadata-Version: 2.1
Name: streamlit-pannellum
Version: 0.0.2
Summary: This library is a streamlit app for panorama, 360/HDRI image show and interact.
Home-page: https://gitlab.com/nicolalandro/streamlit-pannellum
Author: Nicola Landro
Author-email: nicolaxx94@live.it
License: UNKNOWN
Project-URL: Source, https://gitlab.com/nicolalandro/streamlit-pannellum
Keywords: panorama,360,HDRI,streamlit
Platform: UNKNOWN
Requires-Python: >=3.6
